binance_sdk_sub_account/__init__.py
binance_sdk_sub_account/metadata.py
binance_sdk_sub_account/rest_api/__init__.py
binance_sdk_sub_account/rest_api/api/__init__.py
binance_sdk_sub_account/rest_api/api/account_management_api.py
binance_sdk_sub_account/rest_api/api/api_management_api.py
binance_sdk_sub_account/rest_api/api/asset_management_api.py
binance_sdk_sub_account/rest_api/api/managed_sub_account_api.py
binance_sdk_sub_account/rest_api/models/__init__.py
binance_sdk_sub_account/rest_api/models/add_ip_restriction_for_sub_account_api_key_response.py
binance_sdk_sub_account/rest_api/models/create_a_virtual_sub_account_response.py
binance_sdk_sub_account/rest_api/models/delete_ip_list_for_a_sub_account_api_key_response.py
binance_sdk_sub_account/rest_api/models/deposit_assets_into_the_managed_sub_account_response.py
binance_sdk_sub_account/rest_api/models/enable_futures_for_sub_account_response.py
binance_sdk_sub_account/rest_api/models/enable_options_for_sub_account_response.py
binance_sdk_sub_account/rest_api/models/enums.py
binance_sdk_sub_account/rest_api/models/futures_transfer_for_sub_account_response.py
binance_sdk_sub_account/rest_api/models/get_detail_on_sub_accounts_futures_account_response.py
binance_sdk_sub_account/rest_api/models/get_detail_on_sub_accounts_futures_account_v2_response.py
binance_sdk_sub_account/rest_api/models/get_detail_on_sub_accounts_futures_account_v2_response_delivery_account_resp.py
binance_sdk_sub_account/rest_api/models/get_detail_on_sub_accounts_futures_account_v2_response_delivery_account_resp_assets_inner.py
binance_sdk_sub_account/rest_api/models/get_detail_on_sub_accounts_futures_account_v2_response_future_account_resp.py
binance_sdk_sub_account/rest_api/models/get_detail_on_sub_accounts_futures_account_v2_response_future_account_resp_assets_inner.py
binance_sdk_sub_account/rest_api/models/get_detail_on_sub_accounts_margin_account_response.py
binance_sdk_sub_account-3.2.0.dist-info/METADATA
binance_sdk_sub_account-3.2.0.dist-info/WHEEL
binance_sdk_sub_account-3.2.0.dist-info/licenses/LICENCE
binance_sdk_sub_account-3.2.0.dist-info/RECORD
